aryanbhatia_101703107_missing_values/__init__.py
aryanbhatia_101703107_missing_values/missing_values.py
aryanbhatia_101703107_missing_values-0.0.1.dist-info/LICENSE.txt
aryanbhatia_101703107_missing_values-0.0.1.dist-info/METADATA
aryanbhatia_101703107_missing_values-0.0.1.dist-info/WHEEL
aryanbhatia_101703107_missing_values-0.0.1.dist-info/top_level.txt
aryanbhatia_101703107_missing_values-0.0.1.dist-info/RECORD
